.gitignore
DEV.md
LICENSE.txt
MANIFEST.in
README.md
apply-pyannotations.sh
conftest.py
environment.bare.yml
environment.yml
environmentdev.yml
export-conda-environment-yml.sh
lint-fix.sh
mypy.ini
requirements.txt
requirements_dev.txt
requirements_test.txt
requirements_upcoming.txt
setup-python-venv.sh
setup.cfg
setup.py
clerkai/__init__.py
clerkai/nb_helpers.py
clerkai/utils.py
clerkai.egg-info/PKG-INFO
clerkai.egg-info/SOURCES.txt
clerkai.egg-info/dependency_links.txt
clerkai.egg-info/not-zip-safe
clerkai.egg-info/requires.txt
clerkai.egg-info/top_level.txt
clerkai/location_history/__init__.py
clerkai/location_history/defaults.py
clerkai/location_history/flow.py
clerkai/location_history/parse.py
clerkai/location_history/test_flow.py
clerkai/location_history/parsers/__init__.py
clerkai/location_history/parsers/parse_utils.py
clerkai/location_history/parsers/test_parse_utils.py
clerkai/location_history/parsers/exiftool/__init__.py
clerkai/location_history/parsers/exiftool/csv.py
clerkai/location_history/parsers/exiftool/test_csv.py
clerkai/location_history/parsers/exiftool/test_data/dropbox-camera-uploads.edited.csv
clerkai/location_history/parsers/exiftool/test_data/dropbox-camera-uploads.edited.csv.expected.csv
clerkai/location_history/parsers/google/__init__.py
clerkai/location_history/parsers/google/takeout/__init__.py
clerkai/location_history/parsers/google/takeout/json.py
clerkai/location_history/parsers/google/takeout/test_json.py
clerkai/location_history/parsers/google/takeout/test_data/Location History.edited.json
clerkai/location_history/parsers/google/takeout/test_data/Location History.edited.json.expected.csv
clerkai/location_history/test_data/possibly_edited_location_history_by_date_df.expected.csv
clerkai/location_history/test_data/Input/Location History/Location History.edited.json
clerkai/location_history/test_data/Input/Location History/dropbox-camera-uploads.edited.csv
clerkai/location_history/test_data/Input/Location History/location_history_files_editable_data.csv
clerkai/time_tracking/__init__.py
clerkai/time_tracking/defaults.py
clerkai/time_tracking/flow.py
clerkai/time_tracking/parse.py
clerkai/time_tracking/test_parse.py
