Metadata-Version: 2.1
Name: clerkai
Version: 0.2.5
Summary: Tools for extracting, annotating and summarizing transaction, location history and time tracking data from local files
Home-page: https://github.com/clerklabs/python-clerkai
Author: Clerk.ai
Author-email: info@clerk.ai
License: mpl-2.0
Download-URL: https://github.com/clerklabs/python-clerkai/archive/v0.2.5.tar.gz
Platform: UNKNOWN
Classifier: Development Status :: 3 - Alpha
Classifier: Intended Audience :: Developers
Classifier: License :: OSI Approved :: Mozilla Public License 2.0 (MPL 2.0)
Classifier: Programming Language :: Python
Classifier: Programming Language :: Python :: 3
Classifier: Programming Language :: Python :: 3.7
Classifier: Topic :: Scientific/Engineering :: Information Analysis
Classifier: Topic :: Scientific/Engineering :: Artificial Intelligence
Requires-Python: >=3.7
